{
  "-27.527_153.265": {
    "suburb": "Cleveland",
    "bbox": [
      -27.54972,
      -27.504346,
      153.242179,
      153.296332
    ],
    "radius": 3000,
    "country_code": "au",
    "timestamp": 1777774945.6294305
  },
  "-27.507_153.265": {
    "suburb": "Ormiston",
    "bbox": [
      -27.5318168,
      -27.4918168,
      153.2369173,
      153.2769173
    ],
    "radius": 3000,
    "country_code": "au",
    "timestamp": 1777774968.8965092
  },
  "-27.526_153.269": {
    "suburb": "Cleveland",
    "bbox": [
      -27.54972,
      -27.504346,
      153.242179,
      153.296332
    ],
    "radius": 3000,
    "country_code": "au",
    "timestamp": 1777775512.0029302
  },
  "-27.493_153.058": {
    "suburb": "Coorparoo",
    "bbox": [
      -27.515191,
      -27.480821,
      153.047641,
      153.075786
    ],
    "radius": 3000,
    "country_code": "au",
    "timestamp": 1777776228.4145656
  },
  "-27.494_153.062": {
    "suburb": "Coorparoo",
    "bbox": [
      -27.515191,
      -27.480821,
      153.047641,
      153.075786
    ],
    "radius": 3000,
    "country_code": "au",
    "timestamp": 1777777703.934759
  },
  "-27.547_153.265": {
    "suburb": "Cleveland",
    "bbox": [
      -27.54972,
      -27.504346,
      153.242179,
      153.296332
    ],
    "radius": 3000,
    "country_code": "au",
    "timestamp": 1777781564.947993
  },
  "-33.899_151.259": {
    "suburb": "Centennial Square",
    "bbox": [
      -33.91,
      -33.87,
      151.2144444,
      151.2544444
    ],
    "radius": 3000,
    "country_code": "au",
    "timestamp": 1777851061.2853155
  },
  "-33.903_151.254": {
    "suburb": "Waverley",
    "bbox": [
      -33.9079201,
      -33.8961676,
      151.2509474,
      151.2611325
    ],
    "radius": 3000,
    "country_code": "au",
    "timestamp": 1777859243.0875452
  },
  "-33.891_151.249": {
    "suburb": "Centennial Square",
    "bbox": [
      -33.91,
      -33.87,
      151.2144444,
      151.2544444
    ],
    "radius": 3000,
    "country_code": "au",
    "timestamp": 1777859289.2838783
  },
  "-33.891_151.248": {
    "suburb": "Centennial Square",
    "bbox": [
      -33.91,
      -33.87,
      151.2144444,
      151.2544444
    ],
    "radius": 3000,
    "country_code": "au",
    "timestamp": 1777859310.0065594
  },
  "-33.893_151.249": {
    "suburb": "Bondi Junction",
    "bbox": [
      -33.8970872,
      -33.8888918,
      151.2408418,
      151.2597468
    ],
    "radius": 3000,
    "country_code": "au",
    "timestamp": 1777859335.7223518
  },
  "-27.495_153.058": {
    "suburb": "Coorparoo",
    "bbox": [
      -27.515191,
      -27.480821,
      153.047641,
      153.075786
    ],
    "radius": 3000,
    "country_code": "au",
    "timestamp": 1777887666.951945
  }
}